kfwx/H2O2.py
kfwx/H2O2y.py
kfwx/NADHRedox.py
kfwx/__init__.py
kfwx/membrane_potential.py
kfwx/merge_h2o2.py
kfwx/merge_mp.py
kfwx/merge_nadh.py
kfwx/proteomics.py
kfwx-1.0.0.dist-info/LICENSE
kfwx-1.0.0.dist-info/METADATA
kfwx-1.0.0.dist-info/WHEEL
kfwx-1.0.0.dist-info/top_level.txt
kfwx-1.0.0.dist-info/RECORD
