Metadata-Version: 2.1
Name: kfwx
Version: 1.0.0
Summary: A data analysis toolkit for the KFW lab (MacOS X)
Home-page: https://github.com/tiffkwin/KFW
Author: Tiffany Nguyen
License: UNKNOWN
Platform: UNKNOWN
Classifier: Programming Language :: Python :: 2.7
Classifier: License :: OSI Approved :: Apache Software License
Classifier: Operating System :: MacOS :: MacOS X
